Metadata-Version: 2.1
Name: auchann
Version: 0.1.1
Summary: The AuChAnn (Automatic CHAT Annotation) package can generate CHAT annotations based on a transcript-correction pairs of utterances.
Home-page: https://github.com/UUDigitalHumanitieslab/auchann
Author: Digital Humanities Lab, Utrecht University
Author-email: digitalhumanities@uu.nl
License: BSD-3 Clause
Platform: UNKNOWN
Requires-Python: >=3.7
License-File: LICENSE
